{"cameraMode":{"drawMode":0,"name":"Shaded","section":"Shading Mode"},"sceneLighting":true,"audioPlay":false,"sceneViewState":{"m_AlwaysRefresh":false,"showFog":true,"showSkybox":true,"showFlares":true,"showImageEffects":true,"showParticleSystems":true,"showVisualEffectGraphs":true,"m_FxEnabled":true},"in2DMode":false,"pivot":{"x":-26.888015747070314,"y":3.9213151931762697,"z":-0.1627974510192871},"rotation":{"x":-0.004365880507975817,"y":0.9536333680152893,"z":-0.30097129940986636,"w":-0.014020724222064019},"size":8.867513656616211,"orthographic":false}